unitrees/__init__.py
unitrees-1.0.0.dist-info/LICENSE.txt
unitrees-1.0.0.dist-info/METADATA
unitrees-1.0.0.dist-info/WHEEL
unitrees-1.0.0.dist-info/top_level.txt
unitrees-1.0.0.dist-info/RECORD
